richardview/.DS_Store
richardview/__init__.py
richardview/dashboard.py
richardview/demo_dashboard.py
richardview/generic_serial_emulator.py
richardview/generic_widget.py
richardview/minimal_widget.py
richardview/_system/.DS_Store
richardview/_system/__init__.py
richardview/_system/_automation_widget.py
richardview/_system/_data_logging_widget.py
richardview/_system/_serial_widget.py
richardview/_system/_show_hide_widget.py
richardview/built_in_widgets/.DS_Store
richardview/built_in_widgets/__init__.py
richardview/built_in_widgets/async_demo_widget.py
richardview/built_in_widgets/spiciness_widget.py
richardview/built_in_widgets/title_widget.py
richardview/majumdar_lab_widgets/.DS_Store
richardview/majumdar_lab_widgets/__init__.py
richardview/majumdar_lab_widgets/aalborg_dpc_widget.py
richardview/majumdar_lab_widgets/cellkraft_humidifier_widget.py
richardview/majumdar_lab_widgets/control_iot_relay_v1.ino
richardview/majumdar_lab_widgets/iot_relay_widget.py
richardview/majumdar_lab_widgets/mks_mfc_widget.py
richardview/majumdar_lab_widgets/omega_usb_utc_widget.py
richardview/majumdar_lab_widgets/picarro_crd_widget.py
richardview/majumdar_lab_widgets/sri_gc_fid_widget.py
richardview/majumdar_lab_widgets/valco_2_way_valve_widget.py
richardview/majumdar_lab_widgets/valco_8_way_valve_widget.py
richardview/utilities/.DS_Store
richardview/utilities/__init__.py
richardview/utilities/gmail_helper.py
richardview/utilities/serial_port_scanner.py
richardview-0.1.7.dist-info/METADATA
richardview-0.1.7.dist-info/WHEEL
richardview-0.1.7.dist-info/licenses/LICENSE
richardview-0.1.7.dist-info/RECORD
