Metadata-Version: 2.1
Name: richardview
Version: 0.1.7
Summary: A laboratory GUI, data acquisition, and automation package.
Project-URL: Homepage, https://github.com/richardsrandall/richardview
Author-email: Richard Randall <rrandall@stanford.edu>
License-File: LICENSE
Classifier: Operating System :: OS Independent
Classifier: Programming Language :: Python :: 3
Requires-Python: >=3.7
